hierarchical_review_plots/__init__.py
hierarchical_review_plots/heat_map_consistent_altair.py
hierarchical_review_plots/polar_bar_plotly.py
hierarchical_review_plots/tilt_ppda_and_build_up_disruption_altair.py
hierarchical_review_plots/transformations.py
hierarchical_review_plots/weighted_xg_plotly.py
hierarchical_review_plots-0.1.6.dist-info/LICENSE
hierarchical_review_plots-0.1.6.dist-info/WHEEL
hierarchical_review_plots-0.1.6.dist-info/METADATA
hierarchical_review_plots-0.1.6.dist-info/RECORD
