Metadata-Version: 2.1
Name: hierarchical_review_plots
Version: 0.1.6
Summary: Module of hierarchical review plots
Home-page: https://github.com/niesfutbol/hierarchical_review_plots
Author: NIES
Author-email: nepo@nies.futbol
Requires-Python: >=3.9
Classifier: License :: OSI Approved :: GNU General Public License v3 or later (GPLv3+)
Requires-Dist: altair
Requires-Dist: Pillow
Requires-Dist: plotly
